tkit_dcn/__init__.py
tkit_dcn/dcn.py
tkitDCN-0.0.0.3.dist-info/LICENSE
tkitDCN-0.0.0.3.dist-info/METADATA
tkitDCN-0.0.0.3.dist-info/WHEEL
tkitDCN-0.0.0.3.dist-info/top_level.txt
tkitDCN-0.0.0.3.dist-info/RECORD
