Metadata-Version: 2.1
Name: tkitDCN
Version: 0.0.0.3
Summary: Terry toolkit tkitDCN 动态图卷机
Home-page: https://github.com/napoler/tkit_dcn_pytorch
Author: Terry Chan
Author-email: napoler2008@gmail.com
License: UNKNOWN
Platform: UNKNOWN
